{
      "StudyFieldsResponse": {
            "APIVrs": "1.01.05",
            "DataVrs": "2022:10:06 23:25:58.836",
            "Expression": "mesenchymal JOINTSTEM",
            "NStudiesAvail": 430108,
            "NStudiesFound": 10,
            "MinRank": 1,
            "MaxRank": 1000,
            "NStudiesReturned": 10,
            "FieldList": [
                  "StudyFirstSubmitQCDate",
                  "StudyPopulation",
                  "StudyType",
                  "SubmissionMCPReleaseN",
                  "SubmissionReleaseDate",
                  "SubmissionResetDate",
                  "SubmissionUnreleaseDate",
                  "TargetDuration",
                  "UnpostedEventDate",
                  "UnpostedEventType",
                  "UnpostedResponsibleParty",
                  "VersionHolder",
                  "WhyStopped",
                  "NCTId"
            ],
            "StudyFields": [
                  {
                        "Rank": 1,
                        "StudyFirstSubmitQCDate": [
                              "April 27, 2020"
                        ],
                        "StudyPopulation": [],
                        "StudyType": [
                              "Interventional"
                        ],
                        "SubmissionMCPReleaseN": [],
                        "SubmissionReleaseDate": [],
                        "SubmissionResetDate": [],
                        "SubmissionUnreleaseDate": [],
                        "TargetDuration": [],
                        "UnpostedEventDate": [],
                        "UnpostedEventType": [],
                        "UnpostedResponsibleParty": [],
                        "VersionHolder": [
                              "October 07, 2022"
                        ],
                        "WhyStopped": [],
                        "NCTId": [
                              "NCT04368806"
                        ]
                  },
                  {
                        "Rank": 2,
                        "StudyFirstSubmitQCDate": [
                              "April 25, 2018"
                        ],
                        "StudyPopulation": [],
                        "StudyType": [
                              "Interventional"
                        ],
                        "SubmissionMCPReleaseN": [],
                        "SubmissionReleaseDate": [],
                        "SubmissionResetDate": [],
                        "SubmissionUnreleaseDate": [],
                        "TargetDuration": [],
                        "UnpostedEventDate": [],
                        "UnpostedEventType": [],
                        "UnpostedResponsibleParty": [],
                        "VersionHolder": [
                              "October 07, 2022"
                        ],
                        "WhyStopped": [],
                        "NCTId": [
                              "NCT03509025"
                        ]
                  },
                  {
                        "Rank": 3,
                        "StudyFirstSubmitQCDate": [
                              "June 17, 2019"
                        ],
                        "StudyPopulation": [],
                        "StudyType": [
                              "Interventional"
                        ],
                        "SubmissionMCPReleaseN": [],
                        "SubmissionReleaseDate": [],
                        "SubmissionResetDate": [],
                        "SubmissionUnreleaseDate": [],
                        "TargetDuration": [],
                        "UnpostedEventDate": [],
                        "UnpostedEventType": [],
                        "UnpostedResponsibleParty": [],
                        "VersionHolder": [
                              "October 07, 2022"
                        ],
                        "WhyStopped": [],
                        "NCTId": [
                              "NCT03990805"
                        ]
                  },
                  {
                        "Rank": 4,
                        "StudyFirstSubmitQCDate": [
                              "June 9, 2020"
                        ],
                        "StudyPopulation": [],
                        "StudyType": [
                              "Interventional"
                        ],
                        "SubmissionMCPReleaseN": [],
                        "SubmissionReleaseDate": [],
                        "SubmissionResetDate": [],
                        "SubmissionUnreleaseDate": [],
                        "TargetDuration": [],
                        "UnpostedEventDate": [],
                        "UnpostedEventType": [],
                        "UnpostedResponsibleParty": [],
                        "VersionHolder": [
                              "October 07, 2022"
                        ],
                        "WhyStopped": [],
                        "NCTId": [
                              "NCT04427930"
                        ]
                  },
                  {
                        "Rank": 5,
                        "StudyFirstSubmitQCDate": [
                              "March 29, 2021"
                        ],
                        "StudyPopulation": [],
                        "StudyType": [
                              "Interventional"
                        ],
                        "SubmissionMCPReleaseN": [],
                        "SubmissionReleaseDate": [],
                        "SubmissionResetDate": [],
                        "SubmissionUnreleaseDate": [],
                        "TargetDuration": [],
                        "UnpostedEventDate": [],
                        "UnpostedEventType": [],
                        "UnpostedResponsibleParty": [],
                        "VersionHolder": [
                              "October 07, 2022"
                        ],
                        "WhyStopped": [],
                        "NCTId": [
                              "NCT04825730"
                        ]
                  },
                  {
                        "Rank": 6,
                        "StudyFirstSubmitQCDate": [
                              "February 17, 2011"
                        ],
                        "StudyPopulation": [],
                        "StudyType": [
                              "Interventional"
                        ],
                        "SubmissionMCPReleaseN": [],
                        "SubmissionReleaseDate": [],
                        "SubmissionResetDate": [],
                        "SubmissionUnreleaseDate": [],
                        "TargetDuration": [],
                        "UnpostedEventDate": [],
                        "UnpostedEventType": [],
                        "UnpostedResponsibleParty": [],
                        "VersionHolder": [
                              "October 07, 2022"
                        ],
                        "WhyStopped": [],
                        "NCTId": [
                              "NCT01300598"
                        ]
                  },
                  {
                        "Rank": 7,
                        "StudyFirstSubmitQCDate": [
                              "February 2, 2016"
                        ],
                        "StudyPopulation": [],
                        "StudyType": [
                              "Interventional"
                        ],
                        "SubmissionMCPReleaseN": [],
                        "SubmissionReleaseDate": [],
                        "SubmissionResetDate": [],
                        "SubmissionUnreleaseDate": [],
                        "TargetDuration": [],
                        "UnpostedEventDate": [],
                        "UnpostedEventType": [],
                        "UnpostedResponsibleParty": [],
                        "VersionHolder": [
                              "October 07, 2022"
                        ],
                        "WhyStopped": [],
                        "NCTId": [
                              "NCT02674399"
                        ]
                  },
                  {
                        "Rank": 8,
                        "StudyFirstSubmitQCDate": [
                              "December 18, 2016"
                        ],
                        "StudyPopulation": [],
                        "StudyType": [
                              "Interventional"
                        ],
                        "SubmissionMCPReleaseN": [],
                        "SubmissionReleaseDate": [],
                        "SubmissionResetDate": [],
                        "SubmissionUnreleaseDate": [],
                        "TargetDuration": [],
                        "UnpostedEventDate": [],
                        "UnpostedEventType": [],
                        "UnpostedResponsibleParty": [],
                        "VersionHolder": [
                              "October 07, 2022"
                        ],
                        "WhyStopped": [],
                        "NCTId": [
                              "NCT03000712"
                        ]
                  },
                  {
                        "Rank": 9,
                        "StudyFirstSubmitQCDate": [
                              "March 26, 2021"
                        ],
                        "StudyPopulation": [],
                        "StudyType": [
                              "Interventional"
                        ],
                        "SubmissionMCPReleaseN": [],
                        "SubmissionReleaseDate": [],
                        "SubmissionResetDate": [],
                        "SubmissionUnreleaseDate": [],
                        "TargetDuration": [],
                        "UnpostedEventDate": [],
                        "UnpostedEventType": [],
                        "UnpostedResponsibleParty": [],
                        "VersionHolder": [
                              "October 07, 2022"
                        ],
                        "WhyStopped": [],
                        "NCTId": [
                              "NCT04821102"
                        ]
                  },
                  {
                        "Rank": 10,
                        "StudyFirstSubmitQCDate": [
                              "January 14, 2016"
                        ],
                        "StudyPopulation": [],
                        "StudyType": [
                              "Interventional"
                        ],
                        "SubmissionMCPReleaseN": [],
                        "SubmissionReleaseDate": [],
                        "SubmissionResetDate": [],
                        "SubmissionUnreleaseDate": [],
                        "TargetDuration": [],
                        "UnpostedEventDate": [],
                        "UnpostedEventType": [],
                        "UnpostedResponsibleParty": [],
                        "VersionHolder": [
                              "October 07, 2022"
                        ],
                        "WhyStopped": [],
                        "NCTId": [
                              "NCT02658344"
                        ]
                  }
            ]
      }
}