{
      "Rank": 141,
      "Acronym": [],
      "AgreementOtherDetails": [],
      "AgreementPISponsorEmployee": [],
      "AgreementRestrictionType": [],
      "AgreementRestrictiveAgreement": [],
      "ArmGroupDescription": [
            "All patients to receive allogeneic UC-MSCs via intralesional injection"
      ],
      "ArmGroupInterventionName": [
            "Biological: Human umbilical cord mesenchymal stem cells (UC-MSCs)"
      ],
      "ArmGroupLabel": [
            "Human umbilical cord mesenchymal stem cells (UC-MSCs)"
      ],
      "ArmGroupType": [
            "Experimental"
      ],
      "AvailIPDComment": [],
      "AvailIPDId": [],
      "AvailIPDType": [],
      "AvailIPDURL": [],
      "BaselineCategoryTitle": [],
      "BaselineClassDenomCountGroupId": [],
      "NCTId": [
            "NCT05039411"
      ],
      "BaselineClassDenomCountValue": [],
      "BaselineClassDenomUnits": [],
      "BaselineClassTitle": [],
      "BaselineDenomCountGroupId": [],
      "BaselineDenomCountValue": [],
      "BaselineDenomUnits": [],
      "BaselineGroupDescription": [],
      "BaselineGroupId": [],
      "BaselineGroupTitle": [],
      "BaselineMeasureCalculatePct": [],
      "BaselineMeasureDenomCountGroupId": [],
      "BaselineMeasureDenomCountValue": [],
      "BaselineMeasureDenomUnits": [],
      "BaselineMeasureDenomUnitsSelected": [],
      "BaselineMeasureDescription": [],
      "BaselineMeasureDispersionType": [],
      "BaselineMeasureParamType": [],
      "BaselineMeasurePopulationDescription": [],
      "BaselineMeasureTitle": [],
      "BaselineMeasureUnitOfMeasure": [],
      "BaselineMeasurementComment": [],
      "BaselineMeasurementGroupId": [],
      "BaselineMeasurementLowerLimit": [],
      "BaselineMeasurementSpread": [],
      "BaselineMeasurementUpperLimit": [],
      "BaselineMeasurementValue": [],
      "BaselinePopulationDescription": [],
      "BaselineTypeUnitsAnalyzed": [],
      "BioSpecDescription": [],
      "BioSpecRetention": [],
      "BriefSummary": [
            "The primary objective of this study is to demonstrate the safety of allogeneic human umbilical cord mesenchymal stem cells (UC-MSCs) (product code: PF2020-CELL) administered by intralesional injection in patients with Crohn's fistula. The secondary objective is to compare the safety of a single/multiple UC-MSCs injection in a dose escalating manner as well as on the efficacy of stem cells treatment (reepithelialization of the external openings of fistula)"
      ],
      "BriefTitle": [
            "Safety of Allogeneic Human Umbilical Cord Mesenchymal Stem Cells (UC-MSCs) to Treat Perianal Fistulas Patients With Crohn's Disease"
      ],
      "CentralContactEMail": [
            "april@ummc.edu.my"
      ],
      "CentralContactName": [
            "April Camilla Roslani, Prof. Dr."
      ],
      "CentralContactPhone": [
            "+603-7949 2050"
      ],
      "CentralContactPhoneExt": [],
      "CentralContactRole": [
            "Contact"
      ],
      "CollaboratorClass": [
            "OTHER"
      ],
      "CollaboratorName": [
            "University of Malaya"
      ],
      "CompletionDate": [
            "December 31, 2024"
      ],
      "CompletionDateType": [
            "Anticipated"
      ],
      "Condition": [
            "Perianal Fistula Due to Crohn's Disease",
            "Fistula in Ano"
      ],
      "ConditionAncestorId": [
            "D000015212",
            "D000005759",
            "D000005767",
            "D000004066",
            "D000007410",
            "D000020763",
            "D000007412",
            "D000016154",
            "D000012002"
      ],
      "ConditionAncestorTerm": [
            "Inflammatory Bowel Diseases",
            "Gastroenteritis",
            "Gastrointestinal Diseases",
            "Digestive System Diseases",
            "Intestinal Diseases",
            "Pathological Conditions, Anatomical",
            "Intestinal Fistula",
            "Digestive System Fistula",
            "Rectal Diseases"
      ],
      "ConditionBrowseBranchAbbrev": [
            "BC06",
            "All",
            "BC23"
      ],
      "ConditionBrowseBranchName": [
            "Digestive System Diseases",
            "All Conditions",
            "Symptoms and General Pathology"
      ],
      "ConditionBrowseLeafAsFound": [
            "Crohn's Disease",
            "Fistula",
            "Perianal Fistula"
      ],
      "ConditionBrowseLeafId": [
            "M5790",
            "M7684",
            "M13997",
            "M9596",
            "M17069",
            "M8027",
            "M8035",
            "M6407",
            "M21672",
            "M9598",
            "M17768",
            "M13996"
      ],
      "ConditionBrowseLeafName": [
            "Crohn Disease",
            "Fistula",
            "Rectal Fistula",
            "Intestinal Diseases",
            "Inflammatory Bowel Diseases",
            "Gastroenteritis",
            "Gastrointestinal Diseases",
            "Digestive System Diseases",
            "Pathological Conditions, Anatomical",
            "Intestinal Fistula",
            "Digestive System Fistula",
            "Rectal Diseases"
      ],
      "ConditionBrowseLeafRelevance": [
            "high",
            "high",
            "high",
            "low",
            "low",
            "low",
            "low",
            "low",
            "low",
            "low",
            "low",
            "low"
      ],
      "ConditionMeshId": [
            "D000003424",
            "D000012003",
            "D000005402"
      ],
      "ConditionMeshTerm": [
            "Crohn Disease",
            "Rectal Fistula",
            "Fistula"
      ],
      "DelayedPosting": [],
      "DesignAllocation": [
            "N/A"
      ],
      "DesignInterventionModel": [
            "Sequential Assignment"
      ],
      "DesignInterventionModelDescription": [
            "First dose is125 million cells and only proceed to second dose of 150 million cells for patients clinically not recovered after 24 weeks from first dose."
      ],
      "DesignMasking": [
            "None (Open Label)"
      ],
      "DesignMaskingDescription": [],
      "DesignObservationalModel": [],
      "DesignPrimaryPurpose": [
            "Treatment"
      ],
      "DesignTimePerspective": [],
      "DesignWhoMasked": [],
      "DetailedDescription": [
            "Design and Investigation:\n\nDosage and mode of administration\n\nFirst Dosage\n\n125 million cells UC-MSCs to be injected\nProcedure: Patients will undergo surgical localization, curettage of the fistulous tract and closure of the internal opening, with intralesional injection of an indicated dose of UC-MSCs\n\nSecond dosage\n\n150 million cells UC-MSCs to be injected\nProcedure: Patients will undergo surgical localization, curettage of the fistulous tract and closure of the internal opening, with intralesional injection of an indicated dose of UC-MSCs"
      ],
      "DispFirstPostDate": [],
      "DispFirstPostDateType": [],
      "DispFirstSubmitDate": [],
      "DispFirstSubmitQCDate": [],
      "EligibilityCriteria": [
            "Inclusion Criteria:\n\nAdult men and women age 18 years and above.\nDiagnosis of perianal fistulae associated with Crohn's disease refractory to medical therapy.\nPresence of perianal fistula(s) with a maximum of 2 internal openings and a maximum of 3 external openings based on clinical assessment.\nFit for surgery.\n\nExclusion Criteria:\n\nInformed consent refusal.\nPregnancy or breastfeeding women.\nCurrent diagnosis of active cancer or remission for less than 5 years.\nEvidence of active sepsis or significant localised infection.\nPatients with HIV, HBV, HCV or treponema infection, whether active or latent.\nPatients with documented allergies.\nPatients who have received infliximab or any other biologics in the 4 weeks before the cell treatment administration.\nPatients currently receiving, or having received within 1 month prior to enrollment into this clinical trial, any investigational drug.\nPatients with any other co-morbidity/ co-pathologies which is deemed as contraindication to stem cells infusion (infection, administration of steroids)."
      ],
      "EnrollmentCount": [
            "7"
      ],
      "EnrollmentType": [
            "Anticipated"
      ],
      "EventGroupDeathsNumAffected": [],
      "EventGroupDeathsNumAtRisk": [],
      "EventGroupDescription": [],
      "EventGroupId": [],
      "EventGroupOtherNumAffected": [],
      "EventGroupOtherNumAtRisk": [],
      "EventGroupSeriousNumAffected": [],
      "EventGroupSeriousNumAtRisk": [],
      "EventGroupTitle": [],
      "EventsDescription": [],
      "EventsFrequencyThreshold": [],
      "EventsTimeFrame": [],
      "ExpAccTypeIndividual": [],
      "ExpAccTypeIntermediate": [],
      "ExpAccTypeTreatment": [],
      "ExpandedAccessNCTId": [],
      "ExpandedAccessStatusForNCTId": [],
      "FDAAA801Violation": [],
      "FlowAchievementComment": [],
      "FlowAchievementGroupId": [],
      "FlowAchievementNumSubjects": [],
      "FlowAchievementNumUnits": [],
      "FlowDropWithdrawComment": [],
      "FlowDropWithdrawType": [],
      "FlowGroupDescription": [],
      "FlowGroupId": [],
      "FlowGroupTitle": [],
      "FlowMilestoneComment": [],
      "FlowMilestoneType": [],
      "FlowPeriodTitle": [],
      "FlowPreAssignmentDetails": [],
      "FlowReasonComment": [],
      "FlowReasonGroupId": [],
      "FlowReasonNumSubjects": [],
      "FlowReasonNumUnits": [],
      "FlowRecruitmentDetails": [],
      "FlowTypeUnitsAnalyzed": [],
      "Gender": [
            "All"
      ],
      "GenderBased": [],
      "GenderDescription": [],
      "HasExpandedAccess": [
            "No"
      ],
      "HealthyVolunteers": [
            "No"
      ],
      "IPDSharing": [
            "No"
      ],
      "IPDSharingAccessCriteria": [],
      "IPDSharingDescription": [],
      "IPDSharingInfoType": [],
      "IPDSharingTimeFrame": [],
      "IPDSharingURL": [],
      "InterventionAncestorId": [],
      "InterventionAncestorTerm": [],
      "InterventionArmGroupLabel": [
            "Human umbilical cord mesenchymal stem cells (UC-MSCs)"
      ],
      "InterventionBrowseBranchAbbrev": [],
      "InterventionBrowseBranchName": [],
      "InterventionBrowseLeafAsFound": [],
      "InterventionBrowseLeafId": [],
      "InterventionBrowseLeafName": [],
      "InterventionBrowseLeafRelevance": [],
      "InterventionDescription": [
            "All patients to receive 1st dose of 125 million UC-MSCs and the 2nd dose of 150 million UC-MSCs only if patients have no clinical improvement post 24 weeks after 1st dose"
      ],
      "InterventionMeshId": [],
      "InterventionMeshTerm": [],
      "InterventionName": [
            "Human umbilical cord mesenchymal stem cells (UC-MSCs)"
      ],
      "InterventionOtherName": [],
      "InterventionType": [
            "Biological"
      ],
      "IsFDARegulatedDevice": [
            "No"
      ],
      "IsFDARegulatedDrug": [
            "No"
      ],
      "IsPPSD": [],
      "IsUSExport": [],
      "IsUnapprovedDevice": [],
      "Keyword": [
            "Perianal fistula",
            "Crohn's Disease",
            "Umbilical cord mesenchymal stem cells (UC-MSCs)"
      ],
      "LargeDocDate": [],
      "LargeDocFilename": [],
      "LargeDocHasICF": [],
      "LargeDocHasProtocol": [],
      "LargeDocHasSAP": [],
      "LargeDocLabel": [],
      "LargeDocTypeAbbrev": [],
      "LargeDocUploadDate": [],
      "LastKnownStatus": [],
      "LastUpdatePostDate": [
            "March 22, 2022"
      ],
      "LastUpdatePostDateType": [
            "Actual"
      ],
      "LastUpdateSubmitDate": [
            "March 7, 2022"
      ],
      "LeadSponsorClass": [
            "INDUSTRY"
      ],
      "LeadSponsorName": [
            "CryoCord Sdn Bhd"
      ],
      "LimitationsAndCaveatsDescription": [],
      "LocationCity": [
            "Kuala Lumpur"
      ],
      "LocationContactEMail": [
            "april@ummc.edu.my"
      ],
      "LocationContactName": [
            "April Camilla Roslani, Prof. Dr.",
            "April Camilla Roslani, Prof. Dr."
      ],
      "LocationContactPhone": [
            "+603-7949 2050"
      ],
      "LocationContactPhoneExt": [],
      "LocationContactRole": [
            "Contact",
            "Principal Investigator"
      ],
      "LocationCountry": [
            "Malaysia"
      ],
      "LocationFacility": [
            "University of Malaya Medical Centre"
      ],
      "LocationState": [],
      "LocationStatus": [
            "Recruiting"
      ],
      "LocationZip": [
            "59100"
      ],
      "MaximumAge": [],
      "MinimumAge": [
            "18 Years"
      ],
      "NCTIdAlias": [],
      "OfficialTitle": [
            "A Phase I Study of the Safety of Allogeneic Human Umbilical Cord Mesenchymal Stem Cells (UC-MSCs) for Perianal Fistulas in Patients With Crohn's Disease"
      ],
      "OrgClass": [
            "INDUSTRY"
      ],
      "OrgFullName": [
            "CryoCord Sdn Bhd"
      ],
      "OrgStudyId": [
            "CCSB-CT-PF-01-2021 (Ver_01)"
      ],
      "OrgStudyIdDomain": [],
      "OrgStudyIdLink": [],
      "OrgStudyIdType": [],
      "OtherEventAssessmentType": [],
      "OtherEventNotes": [],
      "OtherEventOrganSystem": [],
      "OtherEventSourceVocabulary": [],
      "OtherEventStatsGroupId": [],
      "OtherEventStatsNumAffected": [],
      "OtherEventStatsNumAtRisk": [],
      "OtherEventStatsNumEvents": [],
      "OtherEventTerm": [],
      "OtherOutcomeDescription": [],
      "OtherOutcomeMeasure": [],
      "OtherOutcomeTimeFrame": [],
      "OutcomeAnalysisCILowerLimit": [],
      "OutcomeAnalysisCILowerLimitComment": [],
      "OutcomeAnalysisCINumSides": [],
      "OutcomeAnalysisCIPctValue": [],
      "OutcomeAnalysisCIUpperLimit": [],
      "OutcomeAnalysisCIUpperLimitComment": [],
      "OutcomeAnalysisDispersionType": [],
      "OutcomeAnalysisDispersionValue": [],
      "OutcomeAnalysisEstimateComment": [],
      "OutcomeAnalysisGroupDescription": [],
      "OutcomeAnalysisGroupId": [],
      "OutcomeAnalysisNonInferiorityComment": [],
      "OutcomeAnalysisNonInferiorityType": [],
      "OutcomeAnalysisOtherAnalysisDescription": [],
      "OutcomeAnalysisPValue": [],
      "OutcomeAnalysisPValueComment": [],
      "OutcomeAnalysisParamType": [],
      "OutcomeAnalysisParamValue": [],
      "OutcomeAnalysisStatisticalComment": [],
      "OutcomeAnalysisStatisticalMethod": [],
      "OutcomeAnalysisTestedNonInferiority": [],
      "OutcomeCategoryTitle": [],
      "OutcomeClassDenomCountGroupId": [],
      "OutcomeClassDenomCountValue": [],
      "OutcomeClassDenomUnits": [],
      "OutcomeClassTitle": [],
      "OutcomeDenomCountGroupId": [],
      "OutcomeDenomCountValue": [],
      "OutcomeDenomUnits": [],
      "OutcomeGroupDescription": [],
      "OutcomeGroupId": [],
      "OutcomeGroupTitle": [],
      "OutcomeMeasureAnticipatedPostingDate": [],
      "OutcomeMeasureCalculatePct": [],
      "OutcomeMeasureDenomUnitsSelected": [],
      "OutcomeMeasureDescription": [],
      "OutcomeMeasureDispersionType": [],
      "OutcomeMeasureParamType": [],
      "OutcomeMeasurePopulationDescription": [],
      "OutcomeMeasureReportingStatus": [],
      "OutcomeMeasureTimeFrame": [],
      "OutcomeMeasureTitle": [],
      "OutcomeMeasureType": [],
      "OutcomeMeasureTypeUnitsAnalyzed": [],
      "OutcomeMeasureUnitOfMeasure": [],
      "OutcomeMeasurementComment": [],
      "OutcomeMeasurementGroupId": [],
      "OutcomeMeasurementLowerLimit": [],
      "OutcomeMeasurementSpread": [],
      "OutcomeMeasurementUpperLimit": [],
      "OutcomeMeasurementValue": [],
      "OverallOfficialAffiliation": [
            "Faculty of Medicine, University of Malaya"
      ],
      "OverallOfficialName": [
            "April Camilla Roslani, Prof. Dr."
      ],
      "OverallOfficialRole": [
            "Principal Investigator"
      ],
      "OverallStatus": [
            "Recruiting"
      ],
      "OversightHasDMC": [
            "Yes"
      ],
      "PatientRegistry": [],
      "Phase": [
            "Phase 1"
      ],
      "PointOfContactEMail": [],
      "PointOfContactOrganization": [],
      "PointOfContactPhone": [],
      "PointOfContactPhoneExt": [],
      "PointOfContactTitle": [],
      "PrimaryCompletionDate": [
            "December 31, 2024"
      ],
      "PrimaryCompletionDateType": [
            "Anticipated"
      ],
      "PrimaryOutcomeDescription": [
            "Any composite of perianal sepsis, persistence of the fistula and allergic reaction."
      ],
      "PrimaryOutcomeMeasure": [
            "Incidence of any treatment-emergent adverse events (TE-AEs)"
      ],
      "PrimaryOutcomeTimeFrame": [
            "24 weeks"
      ],
      "ReferenceCitation": [],
      "ReferencePMID": [],
      "ReferenceType": [],
      "RemovedCountry": [],
      "ResponsiblePartyInvestigatorAffiliation": [],
      "ResponsiblePartyInvestigatorFullName": [],
      "ResponsiblePartyInvestigatorTitle": [],
      "ResponsiblePartyOldNameTitle": [],
      "ResponsiblePartyOldOrganization": [],
      "ResponsiblePartyType": [
            "Sponsor"
      ],
      "ResultsFirstPostDate": [],
      "ResultsFirstPostDateType": [],
      "ResultsFirstPostedQCCommentsDate": [],
      "ResultsFirstPostedQCCommentsDateType": [],
      "ResultsFirstSubmitDate": [],
      "ResultsFirstSubmitQCDate": [],
      "RetractionPMID": [],
      "RetractionSource": [],
      "SamplingMethod": [],
      "SecondaryId": [],
      "SecondaryIdDomain": [],
      "SecondaryIdLink": [],
      "SecondaryIdType": [],
      "SecondaryOutcomeDescription": [
            "Mainly on re-epithelialization of external opening"
      ],
      "SecondaryOutcomeMeasure": [
            "Clinical healing"
      ],
      "SecondaryOutcomeTimeFrame": [
            "24 and/or 48 weeks"
      ],
      "SeeAlsoLinkLabel": [],
      "SeeAlsoLinkURL": [],
      "SeriousEventAssessmentType": [],
      "SeriousEventNotes": [],
      "SeriousEventOrganSystem": [],
      "SeriousEventSourceVocabulary": [],
      "SeriousEventStatsGroupId": [],
      "SeriousEventStatsNumAffected": [],
      "SeriousEventStatsNumAtRisk": [],
      "SeriousEventStatsNumEvents": [],
      "SeriousEventTerm": [],
      "StartDate": [
            "March 1, 2022"
      ],
      "StartDateType": [
            "Actual"
      ],
      "StatusVerifiedDate": [
            "March 2022"
      ],
      "StdAge": [
            "Adult",
            "Older Adult"
      ],
      "StudyFirstPostDate": [
            "September 9, 2021"
      ],
      "StudyFirstPostDateType": [
            "Actual"
      ],
      "StudyFirstSubmitDate": [
            "September 1, 2021"
      ],
      "StudyFirstSubmitQCDate": [
            "September 2, 2021"
      ],
      "StudyPopulation": [],
      "StudyType": [
            "Interventional"
      ],
      "SubmissionMCPReleaseN": [],
      "SubmissionReleaseDate": [],
      "SubmissionResetDate": [],
      "SubmissionUnreleaseDate": [],
      "TargetDuration": [],
      "UnpostedEventDate": [],
      "UnpostedEventType": [],
      "UnpostedResponsibleParty": [],
      "VersionHolder": [
            "October 10, 2022"
      ],
      "WhyStopped": []
}